src/modules/waves.sv

module wave_right(
    input wire clk,
    input wire rst,
    output reg[5:0]  LED =6'b000000
);  

reg [2:0] state = 3'b111;

always @(posedge rst) begin state <= 3'b000; end

always @(posedge clk) begin
        case (state)
            3'b000: begin
                state <= 3'b001;
                LED <= 6'b100000;
            end
            3'b001: begin
                state <= 3'b010;
                LED <= 6'b010000;
            end
            3'b010: begin
                state <= 3'b011;
                LED <= 6'b001000;
            end
            3'b011: begin
                state <= 3'b100;
                LED <= 6'b000100;
            end
            3'b100: begin
                state <= 3'b101;
                LED <= 6'b000010;
            end
            3'b101: begin
                state <= 3'b110;
                LED <= 6'b000001;
            end
            3'b110: begin
                state <= 3'b111;
                LED <= 6'b000000;
            end

            default: begin
            end
        endcase
    end

endmodule


module wave_left(
    input wire clk,
    input wire rst,
    output reg[5:0]  LED=6'b000000
);
reg [2:0] state = 3'b111;

always @(posedge rst) begin state <= 3'b000; end

always @(posedge clk) begin
        case (state)
            3'b000: begin
                state <= 3'b001;
                LED = 6'b000001;
            end
            3'b001: begin
                state <= 3'b010;
                LED <= 6'b000010;
            end
            3'b010: begin
                state <= 3'b011;
                LED <= 6'b000100;
            end
            3'b011: begin
                state <= 3'b100;
                LED <= 6'b001000;
            end
            3'b100: begin
                state <= 3'b101;
                LED <= 6'b010000;
            end
            3'b101: begin
                state <= 3'b110;
                LED <= 6'b100000;
            end
            3'b110: begin
                state <= 3'b111;
                LED <= 6'b000000;
            end

            default: begin
            end
        endcase
    end
endmodule

module wave_up(
    input wire clk,
    input wire rst,
    output reg[5:0]  LED
);
reg [2:0] state = 3'b111;
always @(posedge rst) begin state <= 3'b000; end

always @(posedge clk) begin
        case (state)
            3'b000: begin
                state <= 3'b001;
                LED <= 6'b001100;
            end
            3'b001:state <= 3'b010;
            3'b010: begin
                state <= 3'b011;
                LED <= 6'b010010;
            end
            3'b011: state <= 3'b100;
            3'b100: begin
                state <= 3'b101;
                LED <= 6'b100001;
            end
            3'b101: state <= 3'b110;
            3'b110: begin
                state <= 3'b111;
                LED <= 6'b000000;
            end
            default: begin
            end
        endcase
    end
endmodule

module wave_down(
    input wire clk,
    input wire rst,
    output reg[5:0]  LED
);
reg [2:0] state = 3'b111;
always @(posedge rst) begin state <= 3'b000; end

always @(posedge clk) begin
        case (state)
            3'b000: begin
                state <= 3'b001;
                LED <= 6'b000000;
            end
            3'b001:state <= 3'b010;
            3'b010: begin
                state <= 3'b011;
                LED <= 6'b100001;
            end
            3'b011: state <= 3'b100;
            3'b100: begin
                state <= 3'b101;
                LED <= 6'b010010;
            end
            3'b101: state <= 3'b110;
            3'b110: begin
                state <= 3'b111;
                LED <= 6'b001100;
            end
            default: begin
            end
        endcase
    end
endmodule

src/modules/wave_LED.sv
`include "src/modules/waves.sv"
module wave_LED(
    input wire rst,
    input wire clk,
    input reg[2:0] signal,
    input wire start_sequence,
    output reg [5:0] LED
);
parameter CLK_FRE = 50000000;
parameter led_refresh_s = 0.2;
reg[15:0] display_counter= 0;
parameter integer display_clk_max = CLK_FRE * led_refresh_s;
reg display_clk;

wire [5:0] l_out;
wire [5:0] r_out;
wire [5:0] u_out;
wire [5:0] d_out;

wave_left l_inst(.clk(display_clk),.rst(start_sequence),.LED(l_out));
wave_right r_inst(.clk(display_clk),.rst(start_sequence),.LED(r_out));
wave_up u_inst(.clk(display_clk),.rst(start_sequence),.LED(u_out));
wave_down d_inst(.clk(display_clk),.rst(start_sequence),.LED(d_out));


always @(posedge clk) begin
//make the LED counter tick every led_refresh_s seconds

    if(display_counter == display_clk_max) begin
        display_clk <= 1;
        display_counter<=0;
    end
    else begin
        display_counter = display_counter + 1;
        display_clk <= 0;
    end

end



reg [2:0] signal_reg;

always @(posedge clk or posedge rst) begin
    if (rst) begin
        signal_reg <= 3'b000;
        LED <= 6'b000000;
    end else begin
        signal_reg <= signal;
    end
end

always @(*) begin
    case (signal_reg) 
        3'b001: LED <= l_out;
        3'b010: LED <= r_out;
        3'b011: LED <= u_out;
        3'b100: LED <= d_out;
        default: LED <= 6'b000000;
    endcase
end

endmodule

src/tests/wave_LED_tb.sv
// `include "outputs/synth/wave_LED_synth.sv"
// `include "src/modules/wave_LED.sv"
`timescale 1us/ 1ns

module wave_LED_tb();
    reg clk =0;
    reg [2:0] signal;
    wire [5:0] LED;

    wave_LED wave_LED_inst(
        .clk(clk),
        .signal(signal),
        .LED(LED)
    );

    initial
    begin
        forever #1  clk=~clk;
    end

    initial begin
    $monitor("Time=%0t, clk=%b, signal=%b, LED=%b", $time, clk, signal, LED,wave_LED_inst.start_sequence,wave_LED_inst.display_clk,wave_LED_inst.l_inst);
    $dumpfile("outputs/sim/wave_LED_data.vcd");
    $dumpvars(0,clk,signal,LED,wave_LED_inst.start_sequence,wave_LED_inst.display_clk);
        signal = 0;
        #5
        signal = 1;
        #20
        #100
        $finish;
    end

endmodule

outputs/sim/wave_LED_data.vcd
$date
	Sun Jan 12 00:52:42 2025
$end
$version
	Icarus Verilog
$end
$timescale
	1ns
$end
$scope module wave_LED_tb $end
$var reg 1 ! clk $end
$upscope $end
$scope module wave_LED_tb $end
$var reg 3 " signal [2:0] $end
$upscope $end
$scope module wave_LED_tb $end
$var wire 6 # LED [5:0] $end
$upscope $end
$scope module wave_LED_tb $end
$scope module wave_LED_inst $end
$var wire 1 $ start_sequence $end
$upscope $end
$upscope $end
$scope module wave_LED_tb $end
$scope module wave_LED_inst $end
$var reg 1 % display_clk $end
$upscope $end
$upscope $end
$scope module wave_LED_tb $end
$scope module wave_LED_inst $end
$var wire 6 & l_out [5:0] $end
$upscope $end
$upscope $end
$enddefinitions $end
$comment Show the parameter values. $end
$dumpall
$end
#0
$dumpvars
b0 &
x%
0$
bx #
b0 "
0!
$end
#1000
b0 #
0%
1!
#2000
0!
#3000
1%
1!
#4000
0!
#5000
0%
1!
1$
b1 "
#6000
0!
#7000
b1 #
b1 &
1%
1!
#8000
0!
#9000
0%
1!
#10000
0!
#11000
b10 #
b10 &
1%
1!
#12000
0!
#13000
0%
1!
#14000
0!
#15000
b100 #
b100 &
1%
1!
#16000
0!
#17000
0%
1!
#18000
0!
#19000
b1000 #
b1000 &
1%
1!
#20000
0!
#21000
0%
1!
#22000
0!
#23000
b10000 #
b10000 &
1%
1!
#24000
0!
#25000
0%
1!
#26000
0!
#27000
b100000 #
b100000 &
1%
1!
#28000
0!
#29000
0%
1!
#30000
0!
0$
#31000
b0 #
b0 &
1%
1!
#32000
0!
#33000
0%
1!
#34000
0!
#35000
b1 #
b1 &
1%
1!
1$
#36000
0!
#37000
0%
1!
#38000
0!
#39000
b10 #
b10 &
1%
1!
#40000
0!
0$
#41000
0%
1!
#42000
0!
#43000
b1000 #
b100 &
1%
1!
b10 "
#44000
0!
#45000
0%
1!
1$
#46000
0!
#47000
b100000 #
b1 &
1%
1!
#48000
0!
#49000
0%
1!
#50000
0!
#51000
b10000 #
b10 &
1%
1!
#52000
0!
#53000
0%
1!
#54000
0!
#55000
b1000 #
b100 &
1%
1!
#56000
0!
#57000
0%
1!
#58000
0!
#59000
b100 #
b1000 &
1%
1!
#60000
0!
#61000
0%
1!
#62000
0!
#63000
b10 #
b10000 &
1%
1!
#64000
0!
#65000
0%
1!
#66000
0!
#67000
b1 #
b100000 &
1%
1!
#68000
0!
#69000
0%
1!
#70000
0!
#71000
b0 #
b0 &
1%
1!
#72000
0!
#73000
0%
1!
#74000
0!
#75000
1%
1!
b11 "
0$
#76000
0!
#77000
0%
1!
1$
#78000
0!
0$
#79000
b1100 #
b1 &
1%
1!
#80000
0!
#81000
0%
1!
#82000
0!
#83000
b10 &
1%
1!
#84000
0!
#85000
0%
1!
#86000
0!
#87000
b10010 #
b100 &
1%
1!
#88000
0!
#89000
0%
1!
#90000
0!
#91000
b1000 &
1%
1!
#92000
0!
#93000
0%
1!
#94000
0!
#95000
b100001 #
b10000 &
1%
1!
#96000
0!
#97000
0%
1!
#98000
0!
#99000
b100000 &
1%
1!
#100000
0!
#101000
0%
1!
#102000
0!
#103000
b0 #
b0 &
1%
1!
